contextguard/__init__.py
contextguard/core.py
contextguard-0.1.2.dist-info/METADATA
contextguard-0.1.2.dist-info/WHEEL
contextguard-0.1.2.dist-info/top_level.txt
contextguard-0.1.2.dist-info/RECORD
