Metadata-Version: 2.4
Name: contextguard
Version: 0.1.2
Summary: Context-aware decorator to prevent repeated API retries using Redis.
Author: Yerram Mahendra Reddy
Author-email: yerram.mahi@gmail.com
Classifier: Programming Language :: Python :: 3
Classifier: License :: OSI Approved :: MIT License
Classifier: Operating System :: OS Independent
Requires-Python: >=3.7
Requires-Dist: redis
Dynamic: author
Dynamic: author-email
Dynamic: classifier
Dynamic: description
Dynamic: description-content-type
Dynamic: requires-dist
Dynamic: requires-python
Dynamic: summary
